{"commitInfo":{"timestamp":1767228309418,"operation":"STREAMING UPDATE","operationParameters":{"outputMode":"Append","queryId":"c0805773-31b3-427b-a1cb-4ae909ec4fa6","epochId":"235"},"readVersion":234,"isolationLevel":"Serializable","isBlindAppend":true,"operationMetrics":{"numRemovedFiles":"0","numOutputRows":"39","numOutputBytes":"5764","numAddedFiles":"1"},"engineInfo":"Apache-Spark/3.5.3 Delta-Lake/3.3.0","txnId":"dd07a4d2-41f6-4099-b332-82ad97760896"}}
{"txn":{"appId":"c0805773-31b3-427b-a1cb-4ae909ec4fa6","version":235,"lastUpdated":1767228309411}}
{"add":{"path":"part-00000-ee3d95f1-92f5-4fb5-a4a7-dbfa4e78aa1b-c000.snappy.parquet","partitionValues":{},"size":5764,"modificationTime":1767228309371,"dataChange":true,"stats":"{\"numRecords\":39,\"minValues\":{\"key\":\"coinbase\",\"json_payload\":\"{\\\"type\\\": \\\"ticker\\\", \\\"sequence\\\": 1\",\"kafka_ts\":\"2025-12-31T19:45:04.134-05:00\",\"ingest_ts\":\"2025-12-31T19:45:06.958-05:00\"},\"maxValues\":{\"key\":\"coinbase\",\"json_payload\":\"{\\\"type\\\": \\\"ticker\\\", \\\"sequence\\\": 9\",\"kafka_ts\":\"2025-12-31T19:45:06.611-05:00\",\"ingest_ts\":\"2025-12-31T19:45:06.958-05:00\"},\"nullCount\":{\"key\":0,\"json_payload\":0,\"kafka_ts\":0,\"ingest_ts\":0}}"}}
