{"commitInfo":{"timestamp":1767215793254,"operation":"STREAMING UPDATE","operationParameters":{"outputMode":"Append","queryId":"c0805773-31b3-427b-a1cb-4ae909ec4fa6","epochId":"131"},"readVersion":130,"isolationLevel":"Serializable","isBlindAppend":true,"operationMetrics":{"numRemovedFiles":"0","numOutputRows":"4","numOutputBytes":"3234","numAddedFiles":"1"},"engineInfo":"Apache-Spark/3.5.3 Delta-Lake/3.3.0","txnId":"39d8630c-c1a3-49f7-9871-da56c3cefd64"}}
{"txn":{"appId":"c0805773-31b3-427b-a1cb-4ae909ec4fa6","version":131,"lastUpdated":1767215793253}}
{"add":{"path":"part-00000-d15ea081-acc7-454e-9f4e-e86d75af6062-c000.snappy.parquet","partitionValues":{},"size":3234,"modificationTime":1767215793245,"dataChange":true,"stats":"{\"numRecords\":4,\"minValues\":{\"key\":\"coinbase\",\"json_payload\":\"{\\\"type\\\": \\\"ticker\\\", \\\"sequence\\\": 1\",\"kafka_ts\":\"2025-12-31T16:16:31.560-05:00\",\"ingest_ts\":\"2025-12-31T16:16:32.318-05:00\"},\"maxValues\":{\"key\":\"coinbase\",\"json_payload\":\"{\\\"type\\\": \\\"ticker\\\", \\\"sequence\\\": 9\",\"kafka_ts\":\"2025-12-31T16:16:32.279-05:00\",\"ingest_ts\":\"2025-12-31T16:16:32.318-05:00\"},\"nullCount\":{\"key\":0,\"json_payload\":0,\"kafka_ts\":0,\"ingest_ts\":0}}"}}
