{"commitInfo":{"timestamp":1767309056930,"operation":"STREAMING UPDATE","operationParameters":{"outputMode":"Append","queryId":"c0805773-31b3-427b-a1cb-4ae909ec4fa6","epochId":"278"},"readVersion":277,"isolationLevel":"Serializable","isBlindAppend":true,"operationMetrics":{"numRemovedFiles":"0","numOutputRows":"6","numOutputBytes":"3358","numAddedFiles":"1"},"engineInfo":"Apache-Spark/3.5.3 Delta-Lake/3.3.0","txnId":"8bd50723-0b48-47c0-b51f-5c4754660945"}}
{"txn":{"appId":"c0805773-31b3-427b-a1cb-4ae909ec4fa6","version":278,"lastUpdated":1767309056927}}
{"add":{"path":"part-00000-471ca4bb-5fe9-4dbe-b9ad-33b38f64b148-c000.snappy.parquet","partitionValues":{},"size":3358,"modificationTime":1767309056920,"dataChange":true,"stats":"{\"numRecords\":6,\"minValues\":{\"key\":\"coinbase\",\"json_payload\":\"{\\\"type\\\": \\\"ticker\\\", \\\"sequence\\\": 1\",\"kafka_ts\":\"2026-01-01T18:10:51.144-05:00\",\"ingest_ts\":\"2026-01-01T18:10:54.207-05:00\"},\"maxValues\":{\"key\":\"coinbase\",\"json_payload\":\"{\\\"type\\\": \\\"ticker\\\", \\\"sequence\\\": 9\",\"kafka_ts\":\"2026-01-01T18:10:54.168-05:00\",\"ingest_ts\":\"2026-01-01T18:10:54.207-05:00\"},\"nullCount\":{\"key\":0,\"json_payload\":0,\"kafka_ts\":0,\"ingest_ts\":0}}"}}
