{"commitInfo":{"timestamp":1767228347775,"operation":"STREAMING UPDATE","operationParameters":{"outputMode":"Append","queryId":"c0805773-31b3-427b-a1cb-4ae909ec4fa6","epochId":"248"},"readVersion":247,"isolationLevel":"Serializable","isBlindAppend":true,"operationMetrics":{"numRemovedFiles":"0","numOutputRows":"36","numOutputBytes":"5262","numAddedFiles":"1"},"engineInfo":"Apache-Spark/3.5.3 Delta-Lake/3.3.0","txnId":"0568b2e8-2d03-4f41-a131-6ebf3b9bbcb1"}}
{"txn":{"appId":"c0805773-31b3-427b-a1cb-4ae909ec4fa6","version":248,"lastUpdated":1767228347774}}
{"add":{"path":"part-00000-1ccf3e84-67cf-420f-85a2-8e28a583f057-c000.snappy.parquet","partitionValues":{},"size":5262,"modificationTime":1767228347767,"dataChange":true,"stats":"{\"numRecords\":36,\"minValues\":{\"key\":\"coinbase\",\"json_payload\":\"{\\\"type\\\": \\\"ticker\\\", \\\"sequence\\\": 1\",\"kafka_ts\":\"2025-12-31T19:45:44.566-05:00\",\"ingest_ts\":\"2025-12-31T19:45:45.926-05:00\"},\"maxValues\":{\"key\":\"coinbase\",\"json_payload\":\"{\\\"type\\\": \\\"ticker\\\", \\\"sequence\\\": 9\",\"kafka_ts\":\"2025-12-31T19:45:45.617-05:00\",\"ingest_ts\":\"2025-12-31T19:45:45.926-05:00\"},\"nullCount\":{\"key\":0,\"json_payload\":0,\"kafka_ts\":0,\"ingest_ts\":0}}"}}
