{"commitInfo":{"timestamp":1767215774179,"operation":"STREAMING UPDATE","operationParameters":{"outputMode":"Append","queryId":"c0805773-31b3-427b-a1cb-4ae909ec4fa6","epochId":"114"},"readVersion":113,"isolationLevel":"Serializable","isBlindAppend":true,"operationMetrics":{"numRemovedFiles":"0","numOutputRows":"5","numOutputBytes":"3283","numAddedFiles":"1"},"engineInfo":"Apache-Spark/3.5.3 Delta-Lake/3.3.0","txnId":"85bce6c9-9bad-4c89-a7e6-67882b4ea885"}}
{"txn":{"appId":"c0805773-31b3-427b-a1cb-4ae909ec4fa6","version":114,"lastUpdated":1767215774178}}
{"add":{"path":"part-00000-0313976f-7040-4a3a-80f4-5d2789b3dd5f-c000.snappy.parquet","partitionValues":{},"size":3283,"modificationTime":1767215774168,"dataChange":true,"stats":"{\"numRecords\":5,\"minValues\":{\"key\":\"coinbase\",\"json_payload\":\"{\\\"type\\\": \\\"ticker\\\", \\\"sequence\\\": 1\",\"kafka_ts\":\"2025-12-31T16:16:11.374-05:00\",\"ingest_ts\":\"2025-12-31T16:16:12.817-05:00\"},\"maxValues\":{\"key\":\"coinbase\",\"json_payload\":\"{\\\"type\\\": \\\"ticker\\\", \\\"sequence\\\": 2\",\"kafka_ts\":\"2025-12-31T16:16:12.613-05:00\",\"ingest_ts\":\"2025-12-31T16:16:12.817-05:00\"},\"nullCount\":{\"key\":0,\"json_payload\":0,\"kafka_ts\":0,\"ingest_ts\":0}}"}}
