{"commitInfo":{"timestamp":1767309239081,"operation":"STREAMING UPDATE","operationParameters":{"outputMode":"Append","queryId":"c0805773-31b3-427b-a1cb-4ae909ec4fa6","epochId":"312"},"readVersion":311,"isolationLevel":"Serializable","isBlindAppend":true,"operationMetrics":{"numRemovedFiles":"0","numOutputRows":"129","numOutputBytes":"14121","numAddedFiles":"1"},"engineInfo":"Apache-Spark/3.5.3 Delta-Lake/3.3.0","txnId":"8b9322e2-5a9e-48f1-a974-41ff41fa7b2b"}}
{"txn":{"appId":"c0805773-31b3-427b-a1cb-4ae909ec4fa6","version":312,"lastUpdated":1767309239031}}
{"add":{"path":"part-00000-51305ce3-a7b5-4dbe-9ac7-d3ba50bb4093-c000.snappy.parquet","partitionValues":{},"size":14121,"modificationTime":1767309238844,"dataChange":true,"stats":"{\"numRecords\":129,\"minValues\":{\"key\":\"coinbase\",\"json_payload\":\"{\\\"type\\\": \\\"ticker\\\", \\\"sequence\\\": 1\",\"kafka_ts\":\"2026-01-01T18:13:51.420-05:00\",\"ingest_ts\":\"2026-01-01T18:13:55.204-05:00\"},\"maxValues\":{\"key\":\"coinbase\",\"json_payload\":\"{\\\"type\\\": \\\"ticker\\\", \\\"sequence\\\": 9\",\"kafka_ts\":\"2026-01-01T18:13:55.019-05:00\",\"ingest_ts\":\"2026-01-01T18:13:55.204-05:00\"},\"nullCount\":{\"key\":0,\"json_payload\":0,\"kafka_ts\":0,\"ingest_ts\":0}}"}}
